no_more_breakpoints.py
no_more_breakpoints-0.2.0.dist-info/METADATA
no_more_breakpoints-0.2.0.dist-info/WHEEL
no_more_breakpoints-0.2.0.dist-info/entry_points.txt
no_more_breakpoints-0.2.0.dist-info/licenses/LICENSE
no_more_breakpoints-0.2.0.dist-info/RECORD
