Metadata-Version: 2.3
Name: no_more_breakpoints
Version: 0.2.0
Summary: Utility to ensure no more pdb breakpoints are in Python files.
Project-URL: Homepage, https://github.com/kklein/no-more-breakpoints
Project-URL: Bug Tracker, https://github.com/kklein/no-more-breakpoints/issues
Author: kklein
License: MIT License
License-File: LICENSE
Classifier: License :: OSI Approved :: MIT License
Classifier: Operating System :: OS Independent
Classifier: Programming Language :: Python :: 3
Requires-Python: >=3.7
Requires-Dist: click
